larson/__init__.py
larson/command_line.py
larson/parameter_store.py
larson-2.0.2.data/scripts/larson
larson-2.0.2.data/scripts/larson_json_to_vars
larson-2.0.2.dist-info/LICENSE
larson-2.0.2.dist-info/METADATA
larson-2.0.2.dist-info/WHEEL
larson-2.0.2.dist-info/top_level.txt
larson-2.0.2.dist-info/RECORD
